[
    {
        "id": "1",
        "name": "Passport Process",
        "img": "../src/images/services/passport.jpg",
        "description": ""
    },
    {
        "id": "2",
        "name": "Visa Proccess",
        "img": "../src/images/services/Visa1.png",
        "description": ""
    },
    {
        "id": "3",
        "name": "Have a tour",
        "img": "../src/images/services/tourist.jpg",
        "description": ""
    },
    {
        "id": "4",
        "name": " Travel Insurance",
        "img": "../src/images/services/travel-insurance.jpg",
        "description": ""
    },
    {
        "id": "5",
        "name": "Your Tour Guide",
        "img": "../src/images/services/guide.png",
        "description": ""
    },
    {
        "id": "6",
        "name": "Our Health policy",
        "img": "../src/images/services/health.jpg",
        "description": ""
    }
]